sql30/__init__.py
sql30/api.py
sql30/cmd.py
sql30/db.py
sql30/templates/__init__.py
sql30/templates/build-table.js
sql30/templates/index.html
sql30/tests/__init_.py
sql30/tests/__init__.py
sql30/tests/sanity.py
sql30/tests/testPath.py
sql30/tests/test_context.py
sql30/tests/test_misc.py
sql30/tests/test_reviews.py
sql30/tests/test_scale_cube.py
sql30/tests/test_scale_square.py
sql30-0.2.7.dist-info/LICENSE
sql30-0.2.7.dist-info/METADATA
sql30-0.2.7.dist-info/WHEEL
sql30-0.2.7.dist-info/top_level.txt
sql30-0.2.7.dist-info/RECORD
